bstaple/__init__.py
bstaple/algorithm.py
bstaple/random_vars.py
bstaple/sampling.py
bstaple-0.0.5.dist-info/LICENSE
bstaple-0.0.5.dist-info/METADATA
bstaple-0.0.5.dist-info/WHEEL
bstaple-0.0.5.dist-info/RECORD
