Metadata-Version: 2.1
Name: bstaple
Version: 0.0.5
Summary: Bayesian version of STAPLE
Home-page: https://github.com/davideC00/Bayesian-STAPLE
License: MIT
Author: Davide Cazzorla
Author-email: davide.cazzorla@uniba.it
Requires-Python: >=3.9,<4.0
Classifier: License :: OSI Approved :: MIT License
Classifier: Programming Language :: Python :: 3
Classifier: Programming Language :: Python :: 3.9
Classifier: Programming Language :: Python :: 3.10
Classifier: Programming Language :: Python :: 3.11
Classifier: Programming Language :: Python :: 3.12
Requires-Dist: jax (>=0.4.12)
Requires-Dist: jax-tqdm (>=0.2.1)
Requires-Dist: xarray (>=2024.3.0)
